{
    "url" : "http://borderlandsthegame.com/skilltrees/wilhelm.html",
    "assets" :
    {
        "header" : "borderlandsthegame/prsqlskilltree/images/chars/wilhelm/header.png",
        "header-green" : "borderlandsthegame/prsqlskilltree/images/chars/wilhelm/header_green.png",
        "background" : "borderlandsthegame/prsqlskilltree/images/chars/wilhelm/background.png",
        "badge" :"borderlandsthegame/prsqlskilltree/images/chars/wilhelm/badge.png",
        "class" :
            {
                "name" : "狼与圣人",
                "description" : "放出两个小飞机，分别叫做狼和圣人，能够攻击敌人和给你以及队友加血。",
                "stats" :
                    [
						{
                                    "name" : "冷却时间: 42 秒",
                                    "base" : "25",
                                    "multiply" : 1
						},
						{
                                    "name" : "持续时间: 35 秒",
                                    "base" : "25",
                                    "multiply" : 1
						},
						{
                                    "name" : "圣人恢复 2.5% 最大生命值/秒. ",
                                    "base" : "25",
                                    "multiply" : 1
						}


					],
                "levels" : 1

            },
        "panel" :
        [
            {
                "color" : "red",
                "title" : "borderlandsthegame/prsqlskilltree/images/chars/wilhelm/dreadnought/title.png",
                "skills" :
                [
                    {
                        "name" : "副油箱",
                        "description" : "增加狼和圣人的出场时间，同时冷却加快。",
                        "levels" : 5,
                        "position" : 0,
                        "stats" :
                            [
                                {
                                    "name" : "狼和圣人持续时间: +[$] 秒",
                                    "base" : "2",
                                    "multiply" : 1
                                },
                                {
                                    "name" : "狼和圣人冷却时间 Rate: +[$]%",
                                    "base" : "3",
                                    "multiply" : 1
                                }
                            ],
                        "assets" :
                            [
                                "borderlandsthegame/prsqlskilltree/images/chars/wilhelm/dreadnought/0.png",
                                "borderlandsthegame/prsqlskilltree/images/chars/wilhelm/dreadnought/orange/0.png",
                                "borderlandsthegame/prsqlskilltree/images/chars/wilhelm/dreadnought/green/0.png"
                            ]
                    },
                    {
                        "name" : "巩固",
                        "description" : "增加你和狼的最大生命值，同时当圣人在场的时候，你增加所有枪械的伤害。",
                        "levels" : 5,
                        "position" : 2,
                        "stats" :
                            [
                                {
                                    "name" : "最大生命值: +[$]%",
                                    "base" : "3",
                                    "multiply" : 1
                                },
								{
                                    "name" : "狼最大生命值: +[$]%",
                                    "base" : "3",
                                    "multiply" : 1
                                },
								{
                                    "name" : "枪械伤害: +[$]%",
                                    "base" : "4",
                                    "multiply" : 1
                                }
                            ],
                        "assets" :
                            [
                                "borderlandsthegame/prsqlskilltree/images/chars/wilhelm/dreadnought/1.png",
                                "borderlandsthegame/prsqlskilltree/images/chars/wilhelm/dreadnought/orange/1.png",
                                "borderlandsthegame/prsqlskilltree/images/chars/wilhelm/dreadnought/green/1.png"
                            ]
                    },
                    {
                        "name" : "焕发活力",
                        "description" : "圣人偶尔恢复你和队友的盾值和生命。",
                        "levels" : 5,
                        "position" : 3,
                        "stats" :
                            [
                                {
                                    "name" : "偶尔恢复: +[$]% 护盾 容量",
                                    "base" : "8",
                                    "multiply" : 1
                                },
								{
                                    "name" : "圣人恢复: +[$]% 最大生命值/秒.",
                                    "base" : "0.6",
                                    "multiply" : 1
                                }
                            ],
                        "assets" :
                            [
                                "borderlandsthegame/prsqlskilltree/images/chars/wilhelm/dreadnought/2.png",
                                "borderlandsthegame/prsqlskilltree/images/chars/wilhelm/dreadnought/orange/2.png",
                                "borderlandsthegame/prsqlskilltree/images/chars/wilhelm/dreadnought/green/2.png"
                            ]
                    },
                    {
                        "name" : "热沉",
                        "description" : "增加盾充能速度，减少充能冷却时间。该效果在狼和圣人都不在场的时候是双倍的。",
                        "levels" : 5,
                        "position" : 5,
                        "stats" :
                            [
                                {
                                    "name" : "护盾充能速率: +[$]%",
                                    "base" : "6",
                                    "multiply" : 1
                                },
								{
                                    "name" : "护盾充能延迟: -[$]%",
                                    "base" : "4",
                                    "multiply" : 1,
									"sequence" : ["4","7","11","14","17"]
                                }
                            ],
                        "assets" :
                            [
                                "borderlandsthegame/prsqlskilltree/images/chars/wilhelm/dreadnought/3.png",
                                "borderlandsthegame/prsqlskilltree/images/chars/wilhelm/dreadnought/orange/3.png",
                                "borderlandsthegame/prsqlskilltree/images/chars/wilhelm/dreadnought/green/3.png"
                            ]
                    },
                    {
                        "name" : "终结的规则",
                        "description" : "为生命而战换成了'终结的规则'。当你处在终结的规则的时候，你能缓慢地行走和射击，同时能够电到周围的人。当这一状态结束的时候，会产生核爆炸。",
                        "levels" : 1,
                        "position" : 7,
                        "stats" :
                            [
                                {
                                    "name" : "\"至死方休\""
                                }
                            ],
                        "assets" :
                            [
                                "borderlandsthegame/prsqlskilltree/images/chars/wilhelm/dreadnought/4.png",
                                "borderlandsthegame/prsqlskilltree/images/chars/wilhelm/dreadnought/orange/4.png",
                                "borderlandsthegame/prsqlskilltree/images/chars/wilhelm/dreadnought/green/4.png"
                            ]
                    },
                    {
                        "name" : "快速增援",
                        "description" : "杀死一个敌人后，一段时间内主技能加速冷却，同时增加你的移动速度和射速。",
                        "levels" : 5,
                        "position" : 9,
                        "stats" :
                            [
                                {
                                    "name" : "移动速度: +[$]%",
                                    "base" : "3",
                                    "multiply" : 1
                                },
                                {
                                    "name" : "装填速度: +[$]%",
                                    "base" : "8",
                                    "multiply" : 1
                                },
								{
                                    "name" : "主动技 冷却时间 Rate: +[$]%",
                                    "base" : "4",
                                    "multiply" : 1
                                }
                            ],
                        "assets" :
                            [
                                "borderlandsthegame/prsqlskilltree/images/chars/wilhelm/dreadnought/5.png",
                                "borderlandsthegame/prsqlskilltree/images/chars/wilhelm/dreadnought/orange/5.png",
                                "borderlandsthegame/prsqlskilltree/images/chars/wilhelm/dreadnought/green/5.png"
                            ]
                    },
                    {
                        "name" : "零点",
                        "description" : "当圣人被召回，或者需要冷却的时候，它会产生一个疗伤区域。你和你的队友都可以疗伤。",
                        "levels" : 1,
                        "position" : 10,
                        "stats" :
                            [
                                {
                                    "name" : "治疗区域持续时间: 12.0 秒",
									"base" : "1",
                                    "multiply" : 1
                                },
								{
                                    "name" : "恢复 8.0% 最大生命值/秒. ",
									"base" : "1",
                                    "multiply" : 1
                                }
                            ],
                        "assets" :
                            [
                                "borderlandsthegame/prsqlskilltree/images/chars/wilhelm/dreadnought/6.png",
                                "borderlandsthegame/prsqlskilltree/images/chars/wilhelm/dreadnought/orange/6.png",
                                "borderlandsthegame/prsqlskilltree/images/chars/wilhelm/dreadnought/green/6.png"
                            ]
                    },
                    {
                        "name" : "危险品控制系统",
                        "description" : "当你被电，被烧，或者被腐蚀的时候，你和你的队友都会增加对这一元素抗性。",
                        "levels" : 5,
                        "position" : 11,
                        "stats" :
                            [
                                {
                                    "name" : "元素Resistance: +[$]%",
                                    "base" : "17",
                                    "multiply" : 1,
									"sequence" : ["17","29","38","44","50"]
                                }
                            ],
                        "assets" :
                            [
                                "borderlandsthegame/prsqlskilltree/images/chars/wilhelm/dreadnought/7.png",
                                "borderlandsthegame/prsqlskilltree/images/chars/wilhelm/dreadnought/orange/7.png",
                                "borderlandsthegame/prsqlskilltree/images/chars/wilhelm/dreadnought/green/7.png"
                            ]
                    },
                    {
                        "name" : "动能装甲",
                        "description" : "永久增加你最大生命值，近战可能会产生爆炸。敌人越近，越有机会产生爆炸。",
                        "levels" : 5,
                        "position" : 12,
                        "stats" :
                            [
                                {
                                    "name" : "最大生命值:  +[$]%",
                                    "base" : "5",
                                    "multiply" : 1
                                },
                                {
                                    "name" : "爆炸Feedback: 最多 [$]% chance",
                                    "base" : "5",
                                    "multiply" : 1
                                }
                            ],
                        "assets" :
                            [
                                "borderlandsthegame/prsqlskilltree/images/chars/wilhelm/dreadnought/8.png",
                                "borderlandsthegame/prsqlskilltree/images/chars/wilhelm/dreadnought/orange/8.png",
                                "borderlandsthegame/prsqlskilltree/images/chars/wilhelm/dreadnought/green/9.png"
                            ]
                    },
					{
                        "name" : "小强",
                        "description" : "当你被揍，你会叠加小强，小强会降低伤害。如果你几秒钟之内没有被揍，小强叠加就会变少。",
                        "levels" : 5,
                        "position" : 14,
                        "stats" :
                            [
                                {
                                    "name" : "伤害抵抗: [$]%每层",
                                    "base" : "0.1",
                                    "multiply" : 1
                                },
								{
                                    "name" : "Max层数: 100"
                                }
                            ],
                        "assets" :
                            [
                                "borderlandsthegame/prsqlskilltree/images/chars/wilhelm/dreadnought/9.png",
                                "borderlandsthegame/prsqlskilltree/images/chars/wilhelm/dreadnought/orange/9.png",
                                "borderlandsthegame/prsqlskilltree/images/chars/wilhelm/dreadnought/green/9.png"
                            ]
                    },
					{
                        "name" : "过度充能",
                        "description" : "圣人出场的刹那会将你和队友过度充能，过度充能可让你的移动速度，射速，以及装填速度变快，同时还能恢复弹药。",
                        "levels" : 1,
                        "position" : 16,
                        "stats" :
                            [
								{
                                    "name" : "移动速度: +15%",
                                    "base" : "1",
                                    "multiply" : 1
                                },
								{
                                    "name" : "装填速度: +75%",
                                    "base" : "1",
                                    "multiply" : 1
                                },
								{
                                    "name" : "射速: +75%",
                                    "base" : "1",
                                    "multiply" : 1
                                },
								{
                                    "name" : "Ammo 恢复: +10",
                                    "base" : "1",
                                    "multiply" : 1
                                },
								{
                                    "name" : "持续时间: 10 秒",
                                    "base" : "1",
                                    "multiply" : 1
                                }
                            ],
                        "assets" :
                            [
                                "borderlandsthegame/prsqlskilltree/images/chars/wilhelm/dreadnought/10.png",
                                "borderlandsthegame/prsqlskilltree/images/chars/wilhelm/dreadnought/orange/10.png",
                                "borderlandsthegame/prsqlskilltree/images/chars/wilhelm/dreadnought/green/10.png"
                            ]
                    }


                ]
            },
            {
                "color" : "blue",
                "title" : "borderlandsthegame/prsqlskilltree/images/chars/wilhelm/cybercommando/title.png",
                "skills" :
                [
                    {
                        "name" : "专心致志",
                        "description" : "所有激光枪的伤害提升，弹夹加大。",
                        "levels" : 5,
                        "position" : 0,
                        "stats" :
                            [
                                {
                                    "name" : "激光伤害: +[$]%",
                                    "base" : "4",
                                    "multiply" : 1
                                },
                                {
                                    "name" : "激光弹夹容量: +[$]",
                                    "base" : "4",
                                    "multiply" : 1,
									"sequence" : ["4","6","8","10","12"]
                                }
                            ],
                        "assets" :
                            [
                                "borderlandsthegame/prsqlskilltree/images/chars/wilhelm/cybercommando/0.png",
                                "borderlandsthegame/prsqlskilltree/images/chars/wilhelm/cybercommando/orange/0.png",
                                "borderlandsthegame/prsqlskilltree/images/chars/wilhelm/cybercommando/green/0.png"
                            ]
                    },
                    {
                        "name" : "人与机器",
                        "description" : "你和狼的盾值提升，最大生命提升。",
                        "levels" : 5,
                        "position" : 2,
                        "stats" :
                            [
                                {
                                    "name" : "护盾 容量: +[$]%",
                                    "base" : "3",
                                    "multiply" : 1
                                },
                                {
                                    "name" : "最大生命值: +[$]%",
                                    "base" : "3",
                                    "multiply" : 1
                                },
								{
                                    "name" : "狼护盾 容量: +[$]%",
                                    "base" : "5",
                                    "multiply" : 1
                                },
								{
                                    "name" : "狼最大生命值: +[$]%",
                                    "base" : "5",
                                    "multiply" : 1
                                }
                            ],
                        "assets" :
                            [
                                "borderlandsthegame/prsqlskilltree/images/chars/wilhelm/cybercommando/1.png",
                                "borderlandsthegame/prsqlskilltree/images/chars/wilhelm/cybercommando/orange/1.png",
                                "borderlandsthegame/prsqlskilltree/images/chars/wilhelm/cybercommando/green/1.png"
                            ]
                    },
                    {
                        "name" : "一马当先",
                        "description" : "增加枪械伤害。该技能在你伤害敌人5秒之后冷却。然后你5秒不打敌人或者挨揍5秒钟，该技能冷却完毕。",
                        "levels" : 5,
                        "position" : 3,
                        "stats" :
                            [
                                {
                                    "name" : "枪械伤害: +[$]%",
                                    "base" : "8",
                                    "multiply" : 1
                                }
                            ],
                        "assets" :
                            [
                                "borderlandsthegame/prsqlskilltree/images/chars/wilhelm/cybercommando/2.png",
                                "borderlandsthegame/prsqlskilltree/images/chars/wilhelm/cybercommando/orange/2.png",
                                "borderlandsthegame/prsqlskilltree/images/chars/wilhelm/cybercommando/green/2.png"
                            ]
                    },
                    {
                        "name" : "瞄准镜",
                        "description" : "杀死敌人后，在几秒钟之内增加精准度和致命一击伤害。",
                        "levels" : 5,
                        "position" : 5,
                        "stats" :
                            [
                                {
                                    "name" : "致命一击伤害: +[$]%",
                                    "base" : "10",
                                    "multiply" : 1
                                },
								{
                                    "name" : "精准度: +[$]%",
                                    "base" : "5",
                                    "multiply" : 1
                                }
                            ],
                        "assets" :
                            [
                                "borderlandsthegame/prsqlskilltree/images/chars/wilhelm/cybercommando/3.png",
                                "borderlandsthegame/prsqlskilltree/images/chars/wilhelm/cybercommando/orange/3.png",
                                "borderlandsthegame/prsqlskilltree/images/chars/wilhelm/cybercommando/green/3.png"
                            ]
                    },
                    {
                        "name" : "力量之拳",
                        "description" : "机器形态强化武器。近战的爆炸之拳，同时这个拳的打击范围比较广。",
                        "levels" : 1,
                        "position" : 7,
                        "stats" :
                            [
                                {
                                    "name" : "冷却时间: 12 秒"
                                },
								{
                                    "name" : "\"批准使用肉体武力。\""
                                }
                            ],
                        "assets" :
                            [
                                "borderlandsthegame/prsqlskilltree/images/chars/wilhelm/cybercommando/4.png",
                                "borderlandsthegame/prsqlskilltree/images/chars/wilhelm/cybercommando/orange/4.png",
                                "borderlandsthegame/prsqlskilltree/images/chars/wilhelm/cybercommando/green/4.png"
                            ]
                    },
                    {
                        "name" : "紧急响应",
                        "description" : "当盾值为0的时候就会增加你的射速，装填速度以及狼的伤害。有冷却时间。",
                        "levels" : 5,
                        "position" : 9,
                        "stats" :
                            [
                                {
                                    "name" : "装填速度: +[$]%",
                                    "base" : "5",
                                    "multiply" : 1, "add":5
                                },
								{
                                    "name" : "射速: +[$]%",
                                    "base" : "5",
                                    "multiply" : 1, "add":5
                                },
								{
                                    "name" : "狼射速: +[$]%",
                                    "base" : "10",
                                    "multiply" : 1
                                },
								{
                                    "name" : "持续时间: 15 秒",
                                    "base" : "2",
                                    "multiply" : 1
                                }
                            ],
                        "assets" :
                            [
                                "borderlandsthegame/prsqlskilltree/images/chars/wilhelm/cybercommando/5.png",
                                "borderlandsthegame/prsqlskilltree/images/chars/wilhelm/cybercommando/orange/5.png",
                                "borderlandsthegame/prsqlskilltree/images/chars/wilhelm/cybercommando/green/5.png"
                            ]
                    },
                    {
                        "name" : "冲击吸收机",
                        "description" : "机器形态强化大腿。你能一边狂奔，一边射击，不仅不会降低精准度而且会增加枪械伤害。",
                        "levels" : 1,
                        "position" : 10,
                        "stats" :
                            [
                                {
                                    "name" : "枪械伤害: +20%"
                                }
                            ],
                        "assets" :
                            [
                                "borderlandsthegame/prsqlskilltree/images/chars/wilhelm/cybercommando/6.png",
                                "borderlandsthegame/prsqlskilltree/images/chars/wilhelm/cybercommando/orange/6.png",
                                "borderlandsthegame/prsqlskilltree/images/chars/wilhelm/cybercommando/green/6.png"
                            ]
                    },
                    {
                        "name" : "转移力量",
                        "description" : "当你盾值为0，生命低的时候，如果还有敌人在揍你，你就会大幅恢复充盾同时增加伤害抵抗。该技能有冷却时间。",
                        "levels" : 5,
                        "position" : 11,
                        "stats" :
                            [
                                {
                                    "name" : "生命值 Threshold: 30%",
                                    "base" : "1",
                                    "multiply" : 1
                                },
								{
                                    "name" : "冷却时间: 25 秒",
                                    "base" : "1",
                                    "multiply" : 1
                                },
								{
                                    "name" : "持续时间: 3 秒",
                                    "base" : "1",
                                    "multiply" : 1
                                },
								{
                                    "name" : "伤害抗性:  +[$]%",
                                    "base" : "50",
                                    "multiply" : 1,
									"add" : "16.7",
									"sequence":["50.0", "66.7", "75.0", "80.0", "83.3"]
                                },
								{
                                    "name" : "护盾充能 [$]%",
                                    "base" : "20",
                                    "multiply" : 1
                                }
                            ],
                        "assets" :
                            [
                                "borderlandsthegame/prsqlskilltree/images/chars/wilhelm/cybercommando/7.png",
                                "borderlandsthegame/prsqlskilltree/images/chars/wilhelm/cybercommando/orange/7.png",
                                "borderlandsthegame/prsqlskilltree/images/chars/wilhelm/cybercommando/green/7.png"
                            ]
                    },
                    {
                        "name" : "流星拳",
                        "description" : "增加震击攻击范围。",
                        "levels" : 5,
                        "position" : 12,
                        "stats" :
                            [
                                {
                                    "name" : "震击半径: 等级 [$]",
                                    "base" : "1",
                                    "multiply" : 1
                                }
                            ],
                        "assets" :
                            [
                                "borderlandsthegame/prsqlskilltree/images/chars/wilhelm/cybercommando/8.png",
                                "borderlandsthegame/prsqlskilltree/images/chars/wilhelm/cybercommando/orange/8.png",
                                "borderlandsthegame/prsqlskilltree/images/chars/wilhelm/cybercommando/green/8.png"
                            ]
                    },
                    {
                        "name" : "欢迎参加枪展",
                        "description" : "全面增加枪械能力，比如增加伤害，降低后坐力等等。",
                        "levels" : 5,
                        "position" : 14,
                        "stats" :
                            [
                                {
                                    "name" : "武器伤害:  +[$]%",
                                    "base" : "3",
                                    "multiply" : 1
                                },
                                {
                                    "name" : "装填速度: +[$]%",
                                    "base" : "3",
                                    "multiply" : 1,
									"sequence" : ["3","6","8","11","13"]
                                },
								{
                                    "name" : "弹夹容量: +[$]%",
                                    "base" : "3",
                                    "multiply" : 1
                                },
								{
                                    "name" : "精准度: +[$]%",
                                    "base" : "3",
                                    "multiply" : 1,
									"sequence" : ["3","6","8","11","13"]
                                },
								{
                                    "name" : "减少后坐力: +[$]%",
                                    "base" : "3",
                                    "multiply" : 1,
									"sequence" : ["3","6","8","11","13"]
                                }
                            ],
                        "assets" :
                            [
                                "borderlandsthegame/prsqlskilltree/images/chars/wilhelm/cybercommando/9.png",
                                "borderlandsthegame/prsqlskilltree/images/chars/wilhelm/cybercommando/orange/9.png",
                                "borderlandsthegame/prsqlskilltree/images/chars/wilhelm/cybercommando/green/9.png"
                            ]
                    },
                    {
                        "name" : "复仇大炮",
                        "description" : "机器形态强化武器。盾值为0的时候，你就会肩扛复仇大炮，该大炮发射燃烧激光射线。必须经过盾再度充满，再度为0的时候才会再一次使用复仇大炮。",
                        "levels" : 1,
                        "position" : 16,
                        "stats" :
                            [
                                {
                                    "name" : "持续时间: 12 秒."
                                }
                            ],
                        "assets" :
                            [
                                "borderlandsthegame/prsqlskilltree/images/chars/wilhelm/cybercommando/10.png",
                                "borderlandsthegame/prsqlskilltree/images/chars/wilhelm/cybercommando/orange/10.png",
                                "borderlandsthegame/prsqlskilltree/images/chars/wilhelm/cybercommando/green/10.png"
                            ]
                    }
                ]
            },
            {
                "color" : "green",
                "title" : "borderlandsthegame/prsqlskilltree/images/chars/wilhelm/hunterkiller/title.png",
                "skills" :
                [
                    {
                        "name" : "加力燃烧室",
                        "description" : "狼的飞行速度提升，同时提升你的装弹速度和子弹飞行速度。",
                        "levels" : 5,
                        "position" : 0,
                        "stats" :
                            [
                                {
                                    "name" : "狼速度: +[$]%",
                                    "base" : "6",
                                    "multiply" : 1
                                },
								{
                                    "name" : "装填速度: +[$]%",
                                    "base" : "5",
                                    "multiply" : 1
                                },
								{
                                    "name" : "导弹速度: +[$]%",
                                    "base" : "5",
                                    "multiply" : 1
                                }
                            ],
                        "assets" :
                            [
                                "borderlandsthegame/prsqlskilltree/images/chars/wilhelm/hunterkiller/0.png",
                                "borderlandsthegame/prsqlskilltree/images/chars/wilhelm/hunterkiller/orange/0.png",
                                "borderlandsthegame/prsqlskilltree/images/chars/wilhelm/hunterkiller/green/0.png"
                            ]
                    },
                    {
                        "name" : "火力支援",
                        "description" : "增加所有枪械伤害;增加狼的伤害。",
                        "levels" : 5,
                        "position" : 2,
                        "stats" :
                            [
                                {
                                    "name" : "武器伤害: +[$]%",
                                    "base" : "3",
                                    "multiply" : 1
                                },
                                {
                                    "name" : "狼伤害: +[$]%",
                                    "base" : "5",
                                    "multiply" : 1
                                }
                            ],
                        "assets" :
                            [
                                "borderlandsthegame/prsqlskilltree/images/chars/wilhelm/hunterkiller/1.png",
                                "borderlandsthegame/prsqlskilltree/images/chars/wilhelm/hunterkiller/orange/1.png",
                                "borderlandsthegame/prsqlskilltree/images/chars/wilhelm/hunterkiller/green/1.png"
                            ]
                    },
                    {
                        "name" : "毒之闪电",
                        "description" : "狼的射击有一定几率会变成毒之闪电，对对手造成腐蚀伤害，同时枪械和手榴弹的腐蚀伤害几率以及腐蚀伤害数值都有所提升。",
                        "levels" : 5,
                        "position" : 3,
                        "stats" :
                            [
                                {
                                    "name" : "毒之闪电几率: +[$]%",
                                    "base" : "5",
                                    "multiply" : 1, "add":5
                                },
                                {
                                    "name" : "腐蚀几率: +[$]%",
                                    "base" : "2",
                                    "multiply" : 1
                                },
								{
                                    "name" : "腐蚀伤害: +[$]%",
                                    "base" : "4",
                                    "multiply" : 1
                                }
                            ],
                        "assets" :
                            [
                                "borderlandsthegame/prsqlskilltree/images/chars/wilhelm/hunterkiller/2.png",
                                "borderlandsthegame/prsqlskilltree/images/chars/wilhelm/hunterkiller/orange/2.png",
                                "borderlandsthegame/prsqlskilltree/images/chars/wilhelm/hunterkiller/green/2.png"
                            ]
                    },
                    {
                        "name" : "压制",
                        "description" : "杀死一个敌人后，一段时间内，狼和你的射速都有所提升。",
                        "levels" : 5,
                        "position" : 5,
                        "stats" :
                            [
                                {
                                    "name" : "射速: +[$]%",
                                    "base" : "6",
                                    "multiply" : 1
                                },
								{
                                    "name" : "狼射速: +[$]%",
                                    "base" : "15",
                                    "multiply" : 1
                                }
                            ],
                        "assets" :
                            [
                                "borderlandsthegame/prsqlskilltree/images/chars/wilhelm/hunterkiller/3.png",
                                "borderlandsthegame/prsqlskilltree/images/chars/wilhelm/hunterkiller/orange/3.png",
                                "borderlandsthegame/prsqlskilltree/images/chars/wilhelm/hunterkiller/green/3.png"
                            ]
                    },
                    {
                        "name" : "制导激光",
                        "description" : "当狼和圣人都放出来时，会标注敌人。所有对被标注敌人的伤害都会提升。如果敌人被消灭，狼和圣人则能多活动一会儿。",
                        "levels" : 1,
                        "position" : 7,
                        "stats" :
                            [
                                {
                                    "name" : "目标受到伤害: +25%"
                                },
								{
                                    "name" : "狼和圣人持续时间每击杀: +5 秒"
                                }
                            ],
                        "assets" :
                            [
                                "borderlandsthegame/prsqlskilltree/images/chars/wilhelm/hunterkiller/4.png",
                                "borderlandsthegame/prsqlskilltree/images/chars/wilhelm/hunterkiller/orange/4.png",
                                "borderlandsthegame/prsqlskilltree/images/chars/wilhelm/hunterkiller/green/4.png"
                            ]
                    },
                    {
                        "name" : "天雷滚滚",
                        "description" : "当狼出来的时候，你会叠加天雷滚滚，天雷滚滚越多，狼的伤害越大。",
                        "levels" : 5,
                        "position" : 9,
                        "stats" :
                            [
                                {
                                    "name" : "狼伤害: [$]%每层",
                                    "base" : 2,
                                    "multiply" : 1
                                },
                                {
                                    "name" : "层数叠加间隔: 5.0 秒",
                                    "base" : 2,
                                    "multiply" : 1
                                }
                            ],
                        "assets" :
                            [
                                "borderlandsthegame/prsqlskilltree/images/chars/wilhelm/hunterkiller/5.png",
                                "borderlandsthegame/prsqlskilltree/images/chars/wilhelm/hunterkiller/orange/5.png",
                                "borderlandsthegame/prsqlskilltree/images/chars/wilhelm/hunterkiller/green/5.png"
                            ]
                    },
                    {
                        "name" : "杀戮开关",
                        "description" : "当狼被召回，或者它挂球了，或者技能改冷却了。这时候狼就会俯冲轰炸敌人。",
                        "levels" : 1,
                        "position" : 10,
                        "stats" :
                            [
                                {
                                    "name" : "\"神风敢死队\""
                                }
                            ],
                        "assets" :
                            [
                                "borderlandsthegame/prsqlskilltree/images/chars/wilhelm/hunterkiller/6.png",
                                "borderlandsthegame/prsqlskilltree/images/chars/wilhelm/hunterkiller/orange/6.png",
                                "borderlandsthegame/prsqlskilltree/images/chars/wilhelm/hunterkiller/green/6.png"
                            ]
                    },
                    {
                        "name" : "瞎搅和",
                        "description" : "狼挂了，又有一只狼出来顶替它。而且核心技能持续时间增长。",
                        "levels" : 5,
                        "position" : 11,
                        "stats" :
                            [
                                {
                                    "name" : "部署时间增加: [$]%",
                                    "base" : "25",
                                    "multiply" : 1,
									"add" : "5"
                                }
                            ],
                        "assets" :
                            [
                                "borderlandsthegame/prsqlskilltree/images/chars/wilhelm/hunterkiller/7.png",
                                "borderlandsthegame/prsqlskilltree/images/chars/wilhelm/hunterkiller/orange/7.png",
                                "borderlandsthegame/prsqlskilltree/images/chars/wilhelm/hunterkiller/green/7.png"
                            ]
                    },
                    {
                        "name" : "冷战",
                        "description" : "当你造成电击，火焰或者腐蚀伤害的时候，对手有一定几率会冻住。",
                        "levels" : 5,
                        "position" : 12,
                        "stats" :
                            [
                                {
                                    "name" : "冻结几率: +[$]%",
                                    "base" : 5,
                                    "multiply" : 1
                                },
								{
                                    "name" : "冰冻武器冻结几率: +[$]%",
                                    "base" : 2,
                                    "multiply" : 1
                                }
                            ],
                        "assets" :
                            [
                                "borderlandsthegame/prsqlskilltree/images/chars/wilhelm/hunterkiller/8.png",
                                "borderlandsthegame/prsqlskilltree/images/chars/wilhelm/hunterkiller/orange/8.png",
                                "borderlandsthegame/prsqlskilltree/images/chars/wilhelm/hunterkiller/green/8.png"
                            ]
                    },
                    {
                        "name" : "升级",
                        "description" : "增加致命一击的伤害。如果你对敌人造成致命一击，狼和圣人活动时间变长。此技能有冷却时间。",
                        "levels" : 5,
                        "position" : 14,
                        "stats" :
                            [
                                {
                                    "name" : "暴击伤害:  +[$]%",
                                    "base" : "5",
                                    "multiply" : 1
                                },
								{
                                    "name" : "冷却时间抵抗:  [$] 秒",
                                    "base" : ".60",
                                    "multiply" : 1
                                },
								{
                                    "name" : "冷却时间:  6.0 秒",
                                    "base" : ".60",
                                    "multiply" : 1
                                }
                            ],
                        "assets" :
                            [
                                "borderlandsthegame/prsqlskilltree/images/chars/wilhelm/hunterkiller/9.png",
                                "borderlandsthegame/prsqlskilltree/images/chars/wilhelm/hunterkiller/orange/9.png",
                                "borderlandsthegame/prsqlskilltree/images/chars/wilhelm/hunterkiller/green/9.png"
                            ]
                    },
                    {
                        "name" : "欧米茄攻击",
                        "description" : "狼隔一段时间就会对对手发射致命导弹。",
                        "levels" : 1,
                        "position" : 16,
                        "stats" :
                            [
                                {
                                    "name" : "\"枪不好使，改用导弹。\""
                                }
                            ],
                        "assets" :
                            [
                                "borderlandsthegame/prsqlskilltree/images/chars/wilhelm/hunterkiller/10.png",
                                "borderlandsthegame/prsqlskilltree/images/chars/wilhelm/hunterkiller/orange/10.png",
                                "borderlandsthegame/prsqlskilltree/images/chars/wilhelm/hunterkiller/green/10.png"
                            ]
                    }
                ]
            }

        ]
    }

}